<clients>
  <client>
    <nom>Rodríguez</nom>
    <prenom>Carlos</prenom>
    <email>carlos.rodriguez@example.com</email>
  </client>
  <client>
    <nom>García</nom>
    <prenom>Isabella</prenom>
    <email>isabella.garcia@example.com</email>
  </client>
  <client>
    <nom>López</nom>
    <prenom>Diego</prenom>
    <email>diego.lopez@example.com</email>
  </client>
  <client>
    <nom>Hernández</nom>
    <prenom>Sofía</prenom>
    <email>sofia.hernandez@example.com</email>
  </client>
  <client>
    <nom>González</nom>
    <prenom>Alejandro</prenom>
    <email>alejandro.gonzalez@example.com</email>
  </client>
  <client>
    <nom>Martínez</nom>
    <prenom>Valentina</prenom>
    <email>valentina.martinez@example.com</email>
  </client>
  <client>
    <nom>Ramírez</nom>
    <prenom>Mateo</prenom>
    <email>mateo.ramirez@example.com</email>
  </client>
  <client>
    <nom>Fernández</nom>
    <prenom>Camila</prenom>
    <email>camila.fernandez@example.com</email>
  </client>
</clients>